[
  {
    "name": "二世谷滑雪場",
    "address": "北海道虻田郡倶知安町",
    "city": "俱知安町",
    "country": "日本",
    "latitude": 42.8654,
    "longitude": 140.6818,
    "createdAt": "2025-05-01T00:00:00.000Z"
  },
  {
    "name": "苗場滑雪場",
    "address": "新潟縣南魚沼郡湯沢町三國",
    "city": "湯沢町",
    "country": "日本",
    "latitude": 36.8728,
    "longitude": 138.7631,
    "createdAt": "2025-05-02T00:00:00.000Z"
  },
  {
    "name": "札幌國際滑雪場",
    "address": "北海道札幌市南區小金湯",
    "city": "札幌市",
    "country": "日本",
    "latitude": 42.9144,
    "longitude": 141.1439,
    "createdAt": "2025-05-03T00:00:00.000Z"
  }
]
